{
  "restaurant": "merchantsyyc",
  "parsed_at": "2026-02-06T03:21:45.795135",
  "item_count": 132,
  "items": [
    {
      "name": "Cabernet Sauvignon",
      "price": 15.0,
      "description": "Paso Robles, California",
      "category": "WINE",
      "simplified_description": "Paso Robles, California",
      "dietary_info": [],
      "other_info": ""
    },
    {
      "name": "Grenache",
      "price": 13.5,
      "description": "COTES DU RHONE, FRANCE",
      "category": "WINE",
      "simplified_description": "COTES DU RHONE, FRANCE",
      "dietary_info": [],
      "other_info": ""
    },
    {
      "name": "Cabernet Sauvignon",
      "price": 13.5,
      "description": "Languedoc-Roussillon, FRANCE",
      "category": "WINE",
      "simplified_description": "Languedoc-Roussillon, FRANCE",
      "dietary_info": [],
      "other_info": ""
    },
    {
      "name": "Pinot Noir",
      "price": 13.5,
      "description": "VILLAGE DE CESSERAS, FRANCE",
      "category": "WINE",
      "simplified_description": "VILLAGE DE CESSERAS, FRANCE",
      "dietary_info": [],
      "other_info": ""
    },
    {
      "name": "Merlot",
      "price": 15.0,
      "description": "Languedoc, FRANCE",
      "category": "WINE",
      "simplified_description": "Languedoc, FRANCE",
      "dietary_info": [],
      "other_info": ""
    },
    {
      "name": "Cabernet Sauvignon",
      "price": 58.0,
      "description": "BAROSA VALLEY, AUSTRALIA",
      "category": "WINE",
      "simplified_description": "BAROSA VALLEY, AUSTRALIA",
      "dietary_info": [],
      "other_info": ""
    },
    {
      "name": "Red Blend",
      "price": 94.0,
      "description": "RUSSIAN RIVER VALLEY, CALIFORNIA",
      "category": "WINE",
      "simplified_description": "RUSSIAN RIVER VALLEY, CALIFORNIA",
      "dietary_info": [],
      "other_info": ""
    },
    {
      "name": "Grenache, Syrah & Petite Sirah",
      "price": 100.0,
      "description": "NORTHERN CALIFORNIA",
      "category": "WINE",
      "simplified_description": "NORTHERN CALIFORNIA",
      "dietary_info": [],
      "other_info": ""
    },
    {
      "name": "Zinfandel",
      "price": 120.0,
      "description": "California, USA",
      "category": "WINE",
      "simplified_description": "California, USA",
      "dietary_info": [],
      "other_info": ""
    },
    {
      "name": "Cabernet Sauvignon",
      "price": 160.0,
      "description": "napa valley, CALIFORNIA",
      "category": "WINE",
      "simplified_description": "napa valley, CALIFORNIA",
      "dietary_info": [],
      "other_info": ""
    },
    {
      "name": "Red Blend",
      "price": 160.0,
      "description": "COLUMBIA VALLEY, WASHINGTON",
      "category": "WINE",
      "simplified_description": "COLUMBIA VALLEY, WASHINGTON",
      "dietary_info": [],
      "other_info": ""
    },
    {
      "name": "Pinot Noir",
      "price": 50.0,
      "description": "Leyda Valley, Chile",
      "category": "WINE",
      "simplified_description": "Leyda Valley, Chile",
      "dietary_info": [],
      "other_info": ""
    },
    {
      "name": "Pinot Noir",
      "price": 100.0,
      "description": "WILLAMETTE VALLEY, OREGON",
      "category": "WINE",
      "simplified_description": "WILLAMETTE VALLEY, OREGON",
      "dietary_info": [],
      "other_info": ""
    },
    {
      "name": "Shiraz",
      "price": 110.0,
      "description": "COONAWARRA, AUSTRALIA",
      "category": "WINE",
      "simplified_description": "COONAWARRA, AUSTRALIA",
      "dietary_info": [],
      "other_info": ""
    },
    {
      "name": "Grenache, Syrah",
      "price": 80.0,
      "description": "COTES DU RHONE, FRANCE",
      "category": "WINE",
      "simplified_description": "COTES DU RHONE, FRANCE",
      "dietary_info": [],
      "other_info": ""
    },
    {
      "name": "Merlot, Cabernet Franc, Cabernet Sauvignon",
      "price": 120.0,
      "description": "SAINT-EMILION, BOURDEAUX",
      "category": "WINE",
      "simplified_description": "SAINT-EMILION, BOURDEAUX",
      "dietary_info": [],
      "other_info": ""
    },
    {
      "name": "Bordeaux Blend",
      "price": 150.0,
      "description": "MEDOC, BORDEAUX",
      "category": "WINE",
      "simplified_description": "MEDOC, BORDEAUX",
      "dietary_info": [],
      "other_info": ""
    },
    {
      "name": "Bordeaux Red Blend",
      "price": 190.0,
      "description": "PESSAC-LEOGNAN, BORDEAUX",
      "category": "WINE",
      "simplified_description": "PESSAC-LEOGNAN, BORDEAUX",
      "dietary_info": [],
      "other_info": ""
    },
    {
      "name": "Pinot Noir",
      "price": 90.0,
      "description": "BURGUNDY, FRANCE",
      "category": "WINE",
      "simplified_description": "BURGUNDY, FRANCE",
      "dietary_info": [],
      "other_info": ""
    },
    {
      "name": "Malbec",
      "price": 54.0,
      "description": "MENDOZA, ARGENTINA",
      "category": "WINE",
      "simplified_description": "MENDOZA, ARGENTINA",
      "dietary_info": [],
      "other_info": ""
    },
    {
      "name": "Bordeaux Blend",
      "price": 74.0,
      "description": "OKANAGAN VALLEY, BC",
      "category": "WINE",
      "simplified_description": "OKANAGAN VALLEY, BC",
      "dietary_info": [],
      "other_info": ""
    },
    {
      "name": "Barbera del Monferrato",
      "price": 80.0,
      "description": "FRIULI, ITALY",
      "category": "WINE",
      "simplified_description": "FRIULI, ITALY",
      "dietary_info": [],
      "other_info": ""
    },
    {
      "name": "Tuscan Blend",
      "price": 78.0,
      "description": "TUSCANY, ITALY",
      "category": "WINE",
      "simplified_description": "TUSCANY, ITALY",
      "dietary_info": [],
      "other_info": ""
    },
    {
      "name": "Pinot Nero",
      "price": 98.0,
      "description": "VENEZIA, ITALY",
      "category": "WINE",
      "simplified_description": "VENEZIA, ITALY",
      "dietary_info": [],
      "other_info": ""
    },
    {
      "name": "Cabernet Sauvignon",
      "price": 98.0,
      "description": "TUSCANY, ITALY",
      "category": "WINE",
      "simplified_description": "TUSCANY, ITALY",
      "dietary_info": [],
      "other_info": ""
    },
    {
      "name": "Tuscan Blend",
      "price": 104.0,
      "description": "TUSCANY, ITALY",
      "category": "WINE",
      "simplified_description": "TUSCANY, ITALY",
      "dietary_info": [],
      "other_info": ""
    },
    {
      "name": "Nebbiolo",
      "price": 118.0,
      "description": "PIEDMONT, ITALY",
      "category": "WINE",
      "simplified_description": "PIEDMONT, ITALY",
      "dietary_info": [],
      "other_info": ""
    },
    {
      "name": "Barolo",
      "price": 155.0,
      "description": "PIEDMONT, ITALY",
      "category": "WINE",
      "simplified_description": "PIEDMONT, ITALY",
      "dietary_info": [],
      "other_info": ""
    },
    {
      "name": "Merlot",
      "price": 146.0,
      "description": "LAZIO, ITALY",
      "category": "WINE",
      "simplified_description": "LAZIO, ITALY",
      "dietary_info": [],
      "other_info": ""
    },
    {
      "name": "Chianti Classico",
      "price": 140.0,
      "description": "TUSCANY, ITALY",
      "category": "WINE",
      "simplified_description": "TUSCANY, ITALY",
      "dietary_info": [],
      "other_info": ""
    },
    {
      "name": "Brunello di Montalcino",
      "price": 170.0,
      "description": "TUSCANY, ITALY",
      "category": "WINE",
      "simplified_description": "TUSCANY, ITALY",
      "dietary_info": [],
      "other_info": ""
    },
    {
      "name": "Tempranillo",
      "price": 100.0,
      "description": "RIOJA, SPAIN",
      "category": "WINE",
      "simplified_description": "RIOJA, SPAIN",
      "dietary_info": [],
      "other_info": ""
    },
    {
      "name": "Carmenere, Petit Verdot",
      "price": 220.0,
      "description": "COLCHAGUA, CHILE",
      "category": "WINE",
      "simplified_description": "COLCHAGUA, CHILE",
      "dietary_info": [],
      "other_info": ""
    },
    {
      "name": "Cabernet Sauvignon",
      "price": 400.0,
      "description": "MAIPO, CHILE",
      "category": "WINE",
      "simplified_description": "MAIPO, CHILE",
      "dietary_info": [],
      "other_info": ""
    },
    {
      "name": "Barolo",
      "price": 220.0,
      "description": "piedmonte, ITALY",
      "category": "WINE",
      "simplified_description": "piedmonte, ITALY",
      "dietary_info": [],
      "other_info": ""
    },
    {
      "name": "Barbaresco",
      "price": 250.0,
      "description": "piedmonte, ITALY",
      "category": "WINE",
      "simplified_description": "piedmonte, ITALY",
      "dietary_info": [],
      "other_info": ""
    },
    {
      "name": "Tuscan Blend",
      "price": 400.0,
      "description": "TUSCANY, ITALY",
      "category": "WINE",
      "simplified_description": "TUSCANY, ITALY",
      "dietary_info": [],
      "other_info": ""
    },
    {
      "name": "Tuscan Blend",
      "price": 1100.0,
      "description": "TUSCANY, ITALY",
      "category": "WINE",
      "simplified_description": "TUSCANY, ITALY",
      "dietary_info": [],
      "other_info": ""
    },
    {
      "name": "Pinot Noir",
      "price": 170.0,
      "description": "burgundy, france",
      "category": "WINE",
      "simplified_description": "burgundy, france",
      "dietary_info": [],
      "other_info": ""
    },
    {
      "name": "Pinot Noir",
      "price": 300.0,
      "description": "COTES DE NUITS, FRANCE",
      "category": "WINE",
      "simplified_description": "COTES DE NUITS, FRANCE",
      "dietary_info": [],
      "other_info": ""
    },
    {
      "name": "Bordeaux Red Blend",
      "price": 600.0,
      "description": "BORDEAUX, FRANCE",
      "category": "WINE",
      "simplified_description": "BORDEAUX, FRANCE",
      "dietary_info": [],
      "other_info": ""
    },
    {
      "name": "Bordeaux Red Blend",
      "price": 800.0,
      "description": "BORDEAUX, FRANCE",
      "category": "WINE",
      "simplified_description": "BORDEAUX, FRANCE",
      "dietary_info": [],
      "other_info": ""
    },
    {
      "name": "Cabernet Sauvignon, Merlot & Cabernet Franc",
      "price": 200.0,
      "description": "OKANAGAN VALLEY, BC",
      "category": "WINE",
      "simplified_description": "OKANAGAN VALLEY, BC",
      "dietary_info": [],
      "other_info": ""
    },
    {
      "name": "Syrah, Cabernet Sauvignon, Merlot, Cabernet Franc",
      "price": 200.0,
      "description": "OKNAGAN VALLEY, BC",
      "category": "WINE",
      "simplified_description": "OKNAGAN VALLEY, BC",
      "dietary_info": [],
      "other_info": ""
    },
    {
      "name": "Merlot, Cabernet Sauvignon, Cabernet Franc, & Petit Verdot",
      "price": 460.0,
      "description": "SOKANAGAN VALLEY, BC",
      "category": "WINE",
      "simplified_description": "SOKANAGAN VALLEY, BC",
      "dietary_info": [],
      "other_info": ""
    },
    {
      "name": "Merlot",
      "price": 240.0,
      "description": "oliver, BC",
      "category": "WINE",
      "simplified_description": "oliver, BC",
      "dietary_info": [],
      "other_info": ""
    },
    {
      "name": "Cabernet Sauvignon",
      "price": 160.0,
      "description": "RUTHERFORD, NAPA VALLEY",
      "category": "WINE",
      "simplified_description": "RUTHERFORD, NAPA VALLEY",
      "dietary_info": [],
      "other_info": ""
    },
    {
      "name": "Cabernet Sauvignon",
      "price": 240.0,
      "description": "NAPA VALLEY, CALIFORNIA",
      "category": "WINE",
      "simplified_description": "NAPA VALLEY, CALIFORNIA",
      "dietary_info": [],
      "other_info": ""
    },
    {
      "name": "Cabernet Sauvignon",
      "price": 220.0,
      "description": "NAPA VALLEY, CALIFORNIA",
      "category": "WINE",
      "simplified_description": "NAPA VALLEY, CALIFORNIA",
      "dietary_info": [],
      "other_info": ""
    },
    {
      "name": "Cabernet Sauvignon",
      "price": 340.0,
      "description": "ALEXANDER VALLEY, CALIFORNIA",
      "category": "WINE",
      "simplified_description": "ALEXANDER VALLEY, CALIFORNIA",
      "dietary_info": [],
      "other_info": ""
    },
    {
      "name": "Petite Sirah, Syrah & Grenache",
      "price": 180.0,
      "description": "CALIFORNIA, USA",
      "category": "WINE",
      "simplified_description": "CALIFORNIA, USA",
      "dietary_info": [],
      "other_info": ""
    },
    {
      "name": "Cabernet Sauvignon",
      "price": 450.0,
      "description": "NAPA VALLEY, CALIFORNIA",
      "category": "WINE",
      "simplified_description": "NAPA VALLEY, CALIFORNIA",
      "dietary_info": [],
      "other_info": ""
    },
    {
      "name": "Red Blend",
      "price": 420.0,
      "description": "NAPA VALLEY, CALIFORNIA",
      "category": "WINE",
      "simplified_description": "NAPA VALLEY, CALIFORNIA",
      "dietary_info": [],
      "other_info": ""
    },
    {
      "name": "Cabernet Sauvignon",
      "price": 460.0,
      "description": "NAPA VALLEY, CALIFORNA",
      "category": "WINE",
      "simplified_description": "NAPA VALLEY, CALIFORNA",
      "dietary_info": [],
      "other_info": ""
    },
    {
      "name": "Cabernet Sauvignon",
      "price": 630.0,
      "description": "HOWELL MOUNTAIN, NAPA VALLEY",
      "category": "WINE",
      "simplified_description": "HOWELL MOUNTAIN, NAPA VALLEY",
      "dietary_info": [],
      "other_info": ""
    },
    {
      "name": "Cabernet Sauvignon, Merlot",
      "price": 700.0,
      "description": "RUTHERFORD, NAPA VALLEY",
      "category": "WINE",
      "simplified_description": "RUTHERFORD, NAPA VALLEY",
      "dietary_info": [],
      "other_info": ""
    },
    {
      "name": "Cabernet Sauvignon",
      "price": 1000.0,
      "description": "NAPA VALLEY, CALIFORNIA",
      "category": "WINE",
      "simplified_description": "NAPA VALLEY, CALIFORNIA",
      "dietary_info": [],
      "other_info": ""
    },
    {
      "name": "Shiraz",
      "price": 2300.0,
      "description": "SOUTH AUSTRALIA, AUSTRALIA",
      "category": "WINE",
      "simplified_description": "SOUTH AUSTRALIA, AUSTRALIA",
      "dietary_info": [],
      "other_info": ""
    },
    {
      "name": "Coconut margarita - 2oz",
      "price": 14.0,
      "description": "El Tequileno blanco, aperol, coconut syrup, lime juice",
      "category": "DRINK",
      "simplified_description": "El Tequileno blanco, aperol, coconut syrup, lime juice",
      "dietary_info": [],
      "other_info": ""
    },
    {
      "name": "MANGO CHAMOY MARGARITA - 2OZ",
      "price": 15.0,
      "description": "El Tequileno reposado, mango chinola, lime, agave",
      "category": "DRINK",
      "simplified_description": "El Tequileno reposado, mango chinola, lime, agave",
      "dietary_info": [],
      "other_info": ""
    },
    {
      "name": "Casa teal - 2oz",
      "price": 14.0,
      "description": "Casamigos blanco, blue curacao, pineapple, lemon juice, simple syrup",
      "category": "DRINK",
      "simplified_description": "Casamigos blanco, blue curacao, pineapple, lemon juice, simple syrup",
      "dietary_info": [],
      "other_info": ""
    },
    {
      "name": "MAI TAI - 2OZ",
      "price": 14.0,
      "description": "Captain Morgan white rum, dark rum, cointreau, orgeat, lime juice",
      "category": "DRINK",
      "simplified_description": "Captain Morgan white rum, dark rum, cointreau, orgeat, lime juice",
      "dietary_info": [],
      "other_info": ""
    },
    {
      "name": "the staycation - 2oz",
      "price": 14.0,
      "description": "Grey goose orange or citron, peach schnapps, malibu, lemon juice",
      "category": "DRINK",
      "simplified_description": "Grey goose orange or citron, peach schnapps, malibu, lemon juice",
      "dietary_info": [],
      "other_info": ""
    },
    {
      "name": "OLD FASHIONED - 2oz",
      "price": 16.0,
      "description": "Bearface whiskey, simple syrup, bitters",
      "category": "DRINK",
      "simplified_description": "Bearface whiskey, simple syrup, bitters",
      "dietary_info": [],
      "other_info": ""
    },
    {
      "name": "AMARETTO SOUR - 2OZ",
      "price": 14.0,
      "description": "Disaronno, Bearface whiskey, lemon juice, egg white, simple syrup",
      "category": "DRINK",
      "simplified_description": "Disaronno, Bearface whiskey, lemon juice, egg white, simple syrup",
      "dietary_info": [],
      "other_info": ""
    },
    {
      "name": "sour love - 2oz",
      "price": 14.0,
      "description": "Empress rose gin, st. germain elderflower, lime juice, egg white, simple syrup, hibiscus crystal",
      "category": "DRINK",
      "simplified_description": "Empress rose gin, st. germain elderflower, lime juice, egg white, simple syrup, ",
      "dietary_info": [],
      "other_info": ""
    },
    {
      "name": "l'eroy negroni - 2oz",
      "price": 16.0,
      "description": "True tuscan negroni, blend of dry gin, tuscan bitter & red vermouth",
      "category": "DRINK",
      "simplified_description": "True tuscan negroni, blend of dry gin, tuscan bitter & red vermouth",
      "dietary_info": [],
      "other_info": ""
    },
    {
      "name": "MERCHANTS MULE - 2oz",
      "price": 15.0,
      "description": "Ketel one, lime juice, ginger beer",
      "category": "DRINK",
      "simplified_description": "Ketel one, lime juice, ginger beer",
      "dietary_info": [],
      "other_info": ""
    },
    {
      "name": "Pear flower - 2OZ",
      "price": 14.0,
      "description": "Grey goose pear, st.germain elderflower, grapefruit juice, lemon juice, simple syrup",
      "category": "DRINK",
      "simplified_description": "Grey goose pear, st.germain elderflower, grapefruit juice, lemon juice, simple s",
      "dietary_info": [],
      "other_info": ""
    },
    {
      "name": "TERRYS CHOCOLATE ORANGE - 2OZ",
      "price": 14.0,
      "description": "Bearface whiskey, white cacao, cointreau, simple syrup",
      "category": "DRINK",
      "simplified_description": "Bearface whiskey, white cacao, cointreau, simple syrup",
      "dietary_info": [],
      "other_info": ""
    },
    {
      "name": "caipirinha",
      "price": 9.0,
      "description": "Sober rum, lime juice, agave",
      "category": "DRINK",
      "simplified_description": "Sober rum, lime juice, agave",
      "dietary_info": [],
      "other_info": ""
    },
    {
      "name": "MAUI WOWIE",
      "price": 9.0,
      "description": "Seedlip notes de agave, lime juice, agave syrup, pineapple, jalapeno",
      "category": "DRINK",
      "simplified_description": "Seedlip notes de agave, lime juice, agave syrup, pineapple, jalapeno",
      "dietary_info": [],
      "other_info": ""
    },
    {
      "name": "Paloma",
      "price": 9.0,
      "description": "Seedlip grove, grapefruit, lime juice, ginger ale",
      "category": "DRINK",
      "simplified_description": "Seedlip grove, grapefruit, lime juice, ginger ale",
      "dietary_info": [],
      "other_info": ""
    },
    {
      "name": "BOMBAY SAPPHIRE",
      "price": 7.95,
      "description": "",
      "category": "DRINK",
      "simplified_description": "",
      "dietary_info": [],
      "other_info": ""
    },
    {
      "name": "BOTANIST",
      "price": 9.5,
      "description": "",
      "category": "DRINK",
      "simplified_description": "",
      "dietary_info": [],
      "other_info": ""
    },
    {
      "name": "TANQUERAY NO, TEN",
      "price": 9.95,
      "description": "",
      "category": "DRINK",
      "simplified_description": "",
      "dietary_info": [],
      "other_info": ""
    },
    {
      "name": "HENDRICKS",
      "price": 9.95,
      "description": "",
      "category": "DRINK",
      "simplified_description": "",
      "dietary_info": [],
      "other_info": ""
    },
    {
      "name": "EMPRESS 1908",
      "price": 9.95,
      "description": "",
      "category": "DRINK",
      "simplified_description": "",
      "dietary_info": [],
      "other_info": ""
    },
    {
      "name": "CAPTAIN MORGAN BLACK",
      "price": 7.95,
      "description": "",
      "category": "DRINK",
      "simplified_description": "",
      "dietary_info": [],
      "other_info": ""
    },
    {
      "name": "CAPTAIN MORGAN SPICED",
      "price": 7.95,
      "description": "",
      "category": "DRINK",
      "simplified_description": "",
      "dietary_info": [],
      "other_info": ""
    },
    {
      "name": "CAPTAIN MORGAN WHITE",
      "price": 7.95,
      "description": "",
      "category": "DRINK",
      "simplified_description": "",
      "dietary_info": [],
      "other_info": ""
    },
    {
      "name": "APPLETON",
      "price": 8.95,
      "description": "",
      "category": "DRINK",
      "simplified_description": "",
      "dietary_info": [],
      "other_info": ""
    },
    {
      "name": "BUMBU",
      "price": 9.95,
      "description": "",
      "category": "DRINK",
      "simplified_description": "",
      "dietary_info": [],
      "other_info": ""
    },
    {
      "name": "ZAYA",
      "price": 12.95,
      "description": "",
      "category": "DRINK",
      "simplified_description": "",
      "dietary_info": [],
      "other_info": ""
    },
    {
      "name": "RON ZACAPAX O",
      "price": 25.0,
      "description": "",
      "category": "DRINK",
      "simplified_description": "",
      "dietary_info": [],
      "other_info": ""
    },
    {
      "name": "GREY GOOSE - Premium",
      "price": 9.5,
      "description": "Grey Goose Vodka, Orange, Pear and Citron",
      "category": "DRINK",
      "simplified_description": "Grey Goose Vodka, Orange, Pear and Citron",
      "dietary_info": [],
      "other_info": ""
    },
    {
      "name": "van gogh espresso - Premium",
      "price": 8.95,
      "description": "",
      "category": "DRINK",
      "simplified_description": "",
      "dietary_info": [],
      "other_info": ""
    },
    {
      "name": "TITO'S - Premium",
      "price": 8.95,
      "description": "",
      "category": "DRINK",
      "simplified_description": "",
      "dietary_info": [],
      "other_info": ""
    },
    {
      "name": "KETEL ONE - Premium",
      "price": 8.95,
      "description": "",
      "category": "DRINK",
      "simplified_description": "",
      "dietary_info": [],
      "other_info": ""
    },
    {
      "name": "Cîroc - Premium",
      "price": 9.5,
      "description": "",
      "category": "DRINK",
      "simplified_description": "",
      "dietary_info": [],
      "other_info": ""
    },
    {
      "name": "WHITE CLAW MANGO",
      "price": 7.95,
      "description": "",
      "category": "DRINK",
      "simplified_description": "",
      "dietary_info": [],
      "other_info": ""
    },
    {
      "name": "COMPADRE VODKA",
      "price": 7.95,
      "description": "",
      "category": "DRINK",
      "simplified_description": "",
      "dietary_info": [],
      "other_info": ""
    },
    {
      "name": "STOLI BLUEBERRY",
      "price": 7.95,
      "description": "",
      "category": "DRINK",
      "simplified_description": "",
      "dietary_info": [],
      "other_info": ""
    },
    {
      "name": "STOLI RASPBERRY",
      "price": 7.95,
      "description": "",
      "category": "DRINK",
      "simplified_description": "",
      "dietary_info": [],
      "other_info": ""
    },
    {
      "name": "CROWN ROYAL",
      "price": 7.95,
      "description": "",
      "category": "DRINK",
      "simplified_description": "",
      "dietary_info": [],
      "other_info": ""
    },
    {
      "name": "STAMPede RYE EAU CLAIRE",
      "price": 7.95,
      "description": "",
      "category": "DRINK",
      "simplified_description": "",
      "dietary_info": [],
      "other_info": ""
    },
    {
      "name": "PORCH GIN just peachy",
      "price": 8.0,
      "description": "",
      "category": "DRINK",
      "simplified_description": "",
      "dietary_info": [],
      "other_info": ""
    },
    {
      "name": "PORCH PINK LEMONADE",
      "price": 8.0,
      "description": "",
      "category": "DRINK",
      "simplified_description": "",
      "dietary_info": [],
      "other_info": ""
    },
    {
      "name": "PORCH GIN GARDEN",
      "price": 8.0,
      "description": "",
      "category": "DRINK",
      "simplified_description": "",
      "dietary_info": [],
      "other_info": ""
    },
    {
      "name": "TIGER'S TEA",
      "price": 8.0,
      "description": "",
      "category": "DRINK",
      "simplified_description": "",
      "dietary_info": [],
      "other_info": ""
    },
    {
      "name": "PATRÓN SILVER - Premium",
      "price": 12.95,
      "description": "",
      "category": "DRINK",
      "simplified_description": "",
      "dietary_info": [],
      "other_info": ""
    },
    {
      "name": "PATRÓN REPOSADO - Premium",
      "price": 14.95,
      "description": "",
      "category": "DRINK",
      "simplified_description": "",
      "dietary_info": [],
      "other_info": ""
    },
    {
      "name": "PATRÓN AñEJO - Premium",
      "price": 16.95,
      "description": "",
      "category": "DRINK",
      "simplified_description": "",
      "dietary_info": [],
      "other_info": ""
    },
    {
      "name": "CASAMIGOS BLANCO - Premium",
      "price": 13.95,
      "description": "",
      "category": "DRINK",
      "simplified_description": "",
      "dietary_info": [],
      "other_info": ""
    },
    {
      "name": "CASAMIGOS REPOSADO - Premium",
      "price": 15.95,
      "description": "",
      "category": "DRINK",
      "simplified_description": "",
      "dietary_info": [],
      "other_info": ""
    },
    {
      "name": "CASAMIGOS ANEJO - Premium",
      "price": 17.95,
      "description": "",
      "category": "DRINK",
      "simplified_description": "",
      "dietary_info": [],
      "other_info": ""
    },
    {
      "name": "CASAMIGOS MEZCAL - Premium",
      "price": 17.95,
      "description": "",
      "category": "DRINK",
      "simplified_description": "",
      "dietary_info": [],
      "other_info": ""
    },
    {
      "name": "DON JULIO REPOSADO - Premium",
      "price": 12.5,
      "description": "",
      "category": "DRINK",
      "simplified_description": "",
      "dietary_info": [],
      "other_info": ""
    },
    {
      "name": "DON JULIO AñEJO - Premium",
      "price": 13.5,
      "description": "",
      "category": "DRINK",
      "simplified_description": "",
      "dietary_info": [],
      "other_info": ""
    },
    {
      "name": "EL TEQUILENO SASSENACH SELECT - Premium",
      "price": 18.95,
      "description": "",
      "category": "DRINK",
      "simplified_description": "",
      "dietary_info": [],
      "other_info": ""
    },
    {
      "name": "CLASE AZUL REPOSADO - Premium",
      "price": 35.0,
      "description": "",
      "category": "DRINK",
      "simplified_description": "",
      "dietary_info": [],
      "other_info": ""
    },
    {
      "name": "el tequileno BLANCO",
      "price": 7.95,
      "description": "",
      "category": "DRINK",
      "simplified_description": "",
      "dietary_info": [],
      "other_info": ""
    },
    {
      "name": "el tequileno REPOSADO",
      "price": 7.95,
      "description": "",
      "category": "DRINK",
      "simplified_description": "",
      "dietary_info": [],
      "other_info": ""
    },
    {
      "name": "CHIVAS REGAL",
      "price": 7.95,
      "description": "",
      "category": "DRINK",
      "simplified_description": "",
      "dietary_info": [],
      "other_info": ""
    },
    {
      "name": "GLENMORANGIE 10 YEAR",
      "price": 8.95,
      "description": "",
      "category": "DRINK",
      "simplified_description": "",
      "dietary_info": [],
      "other_info": ""
    },
    {
      "name": "GLENLIVET 12 YEAR",
      "price": 8.95,
      "description": "",
      "category": "DRINK",
      "simplified_description": "",
      "dietary_info": [],
      "other_info": ""
    },
    {
      "name": "GLENFIDDICH 12 YEAR",
      "price": 8.95,
      "description": "",
      "category": "DRINK",
      "simplified_description": "",
      "dietary_info": [],
      "other_info": ""
    },
    {
      "name": "HIGHLAND PARK 12 YEAR",
      "price": 10.95,
      "description": "",
      "category": "DRINK",
      "simplified_description": "",
      "dietary_info": [],
      "other_info": ""
    },
    {
      "name": "OBAN 14 YEAR",
      "price": 14.95,
      "description": "",
      "category": "DRINK",
      "simplified_description": "",
      "dietary_info": [],
      "other_info": ""
    },
    {
      "name": "THE MACALLAN 15 YEAR",
      "price": 28.0,
      "description": "",
      "category": "DRINK",
      "simplified_description": "",
      "dietary_info": [],
      "other_info": ""
    },
    {
      "name": "JOHNNIE WALKER BLUE LABEL",
      "price": 32.25,
      "description": "",
      "category": "DRINK",
      "simplified_description": "",
      "dietary_info": [],
      "other_info": ""
    },
    {
      "name": "THE DALMORE 18 YEAR",
      "price": 35.95,
      "description": "",
      "category": "DRINK",
      "simplified_description": "",
      "dietary_info": [],
      "other_info": ""
    },
    {
      "name": "bearface",
      "price": 7.95,
      "description": "",
      "category": "DRINK",
      "simplified_description": "",
      "dietary_info": [],
      "other_info": ""
    },
    {
      "name": "JAMESON",
      "price": 7.95,
      "description": "",
      "category": "DRINK",
      "simplified_description": "",
      "dietary_info": [],
      "other_info": ""
    },
    {
      "name": "JACK DANIEL'S",
      "price": 7.95,
      "description": "",
      "category": "DRINK",
      "simplified_description": "",
      "dietary_info": [],
      "other_info": ""
    },
    {
      "name": "JACK DANIEL'S HONEY",
      "price": 7.95,
      "description": "",
      "category": "DRINK",
      "simplified_description": "",
      "dietary_info": [],
      "other_info": ""
    },
    {
      "name": "MAKERS MARK",
      "price": 7.95,
      "description": "",
      "category": "DRINK",
      "simplified_description": "",
      "dietary_info": [],
      "other_info": ""
    },
    {
      "name": "KNOB CREEK",
      "price": 8.95,
      "description": "",
      "category": "DRINK",
      "simplified_description": "",
      "dietary_info": [],
      "other_info": ""
    },
    {
      "name": "WOODFORD RESERVE",
      "price": 9.95,
      "description": "",
      "category": "DRINK",
      "simplified_description": "",
      "dietary_info": [],
      "other_info": ""
    },
    {
      "name": "ANGEL'S ENVY BOURBON",
      "price": 14.95,
      "description": "",
      "category": "DRINK",
      "simplified_description": "",
      "dietary_info": [],
      "other_info": ""
    },
    {
      "name": "D'USSE VSOP",
      "price": 13.0,
      "description": "",
      "category": "DRINK",
      "simplified_description": "",
      "dietary_info": [],
      "other_info": ""
    },
    {
      "name": "REMY MARTIN VSOP",
      "price": 14.0,
      "description": "",
      "category": "DRINK",
      "simplified_description": "",
      "dietary_info": [],
      "other_info": ""
    }
  ]
}