{
  "restaurant": "silvercitycalgary",
  "parsed_at": "2026-02-06T04:07:59.488653",
  "item_count": 12,
  "items": [
    {
      "name": "80. Chicken Fried Rice 鸡肉炒饭",
      "price": 15.65,
      "description": "80. Chicken Fried Rice 鸡肉炒饭",
      "category": "FOOD",
      "simplified_description": "80. Chicken Fried Rice 鸡肉炒饭",
      "dietary_info": [],
      "other_info": ""
    },
    {
      "name": "48. Ginger Beef 干牛丝",
      "price": 18.75,
      "description": "48. Ginger Beef 干牛丝",
      "category": "FOOD",
      "simplified_description": "48. Ginger Beef 干牛丝",
      "dietary_info": [],
      "other_info": ""
    },
    {
      "name": "3. Pork Dumplings (12 pcs) 锅贴",
      "price": 16.95,
      "description": "3. Pork Dumplings (12 pcs) 锅贴",
      "category": "FOOD",
      "simplified_description": "3. Pork Dumplings (12 pcs) 锅贴",
      "dietary_info": [],
      "other_info": ""
    },
    {
      "name": "40A. Sweet & Sour Chicken Balls 甜酸鸡球",
      "price": 18.75,
      "description": "40A. Sweet & Sour Chicken Balls 甜酸鸡球",
      "category": "FOOD",
      "simplified_description": "40A. Sweet & Sour Chicken Balls 甜酸鸡球",
      "dietary_info": [],
      "other_info": ""
    },
    {
      "name": "79A. House Special Fried Rice 扬州炒饭",
      "price": 17.65,
      "description": "79A. House Special Fried Rice 扬州炒饭",
      "category": "FOOD",
      "simplified_description": "79A. House Special Fried Rice 扬州炒饭",
      "dietary_info": [],
      "other_info": ""
    },
    {
      "name": "57. Pineapple Sweet & Sour Boneless Pork 咕噜肉",
      "price": 18.75,
      "description": "57. Pineapple Sweet & Sour Boneless Pork 咕噜肉",
      "category": "FOOD",
      "simplified_description": "57. Pineapple Sweet & Sour Boneless Pork 咕噜肉",
      "dietary_info": [],
      "other_info": ""
    },
    {
      "name": "48. Ginger Beef 干牛丝",
      "price": 18.75,
      "description": "48. Ginger Beef 干牛丝",
      "category": "FOOD",
      "simplified_description": "48. Ginger Beef 干牛丝",
      "dietary_info": [],
      "other_info": ""
    },
    {
      "name": "80. Chicken Fried Rice 鸡肉炒饭",
      "price": 15.65,
      "description": "80. Chicken Fried Rice 鸡肉炒饭",
      "category": "FOOD",
      "simplified_description": "80. Chicken Fried Rice 鸡肉炒饭",
      "dietary_info": [],
      "other_info": ""
    },
    {
      "name": "3. Pork Dumplings (12 pcs) 锅贴",
      "price": 16.95,
      "description": "3. Pork Dumplings (12 pcs) 锅贴",
      "category": "FOOD",
      "simplified_description": "3. Pork Dumplings (12 pcs) 锅贴",
      "dietary_info": [],
      "other_info": ""
    },
    {
      "name": "40A. Sweet & Sour Chicken Balls 甜酸鸡球",
      "price": 18.75,
      "description": "40A. Sweet & Sour Chicken Balls 甜酸鸡球",
      "category": "FOOD",
      "simplified_description": "40A. Sweet & Sour Chicken Balls 甜酸鸡球",
      "dietary_info": [],
      "other_info": ""
    },
    {
      "name": "79A. House Special Fried Rice 扬州炒饭",
      "price": 17.65,
      "description": "79A. House Special Fried Rice 扬州炒饭",
      "category": "FOOD",
      "simplified_description": "79A. House Special Fried Rice 扬州炒饭",
      "dietary_info": [],
      "other_info": ""
    },
    {
      "name": "57. Pineapple Sweet & Sour Boneless Pork 咕噜肉",
      "price": 18.75,
      "description": "57. Pineapple Sweet & Sour Boneless Pork 咕噜肉",
      "category": "FOOD",
      "simplified_description": "57. Pineapple Sweet & Sour Boneless Pork 咕噜肉",
      "dietary_info": [],
      "other_info": ""
    }
  ]
}